{
  "last_updated": "2026-01-19T01:22:00Z",
  "run_id": "21122053267",
  "critical_vulnerability_found": false,
  "docker_in_docker_patched": true,
  "patch_version": "v0.9.1",
  "techniques": [
    {"name": "UDP to Port 80 (Non-DNS)", "category": "Protocol-level bypass", "description": "UDP packets to port 80 instead of TCP", "result": "failure", "date": "2026-01-19", "details": "No response - UDP not handled"},
    {"name": "DNS NULL Record Query", "category": "DNS-based attack", "description": "Query NULL record type for example.com", "result": "failure", "date": "2026-01-19", "details": "DNS works but provides no HTTP access path"},
    {"name": "DNS SRV Record Query", "category": "DNS-based attack", "description": "Query SRV record _http._tcp.example.com", "result": "failure", "date": "2026-01-19", "details": "DNS works but provides no HTTP access path"},
    {"name": "Container Capabilities Analysis", "category": "Container escape", "description": "Check for CAP_NET_RAW and CAP_NET_ADMIN capabilities", "result": "failure", "date": "2026-01-19", "details": "No dangerous capabilities present"},
    {"name": "Unshare Namespace Manipulation", "category": "Container escape", "description": "Attempt unshare -n to create new network namespace", "result": "failure", "date": "2026-01-19", "details": "Operation not permitted"},
    {"name": "/proc/sys/net Manipulation", "category": "Network stack manipulation", "description": "Read/modify kernel network parameters", "result": "failure", "date": "2026-01-19", "details": "Readable but no write access, no escape path"},
    {"name": "HTTP Expect 100-continue Smuggling", "category": "Application-level smuggling", "description": "POST with Expect: 100-continue header", "result": "failure", "date": "2026-01-19", "details": "400 Bad Request from Squid"},
    {"name": "HTTP OPTIONS with Max-Forwards", "category": "Proxy bypass", "description": "OPTIONS * with Max-Forwards: 0", "result": "failure", "date": "2026-01-19", "details": "501 Not Implemented"},
    {"name": "Netlink Socket Communication", "category": "Network stack manipulation", "description": "AF_NETLINK socket to communicate with kernel", "result": "failure", "date": "2026-01-19", "details": "Socket created but no network bypass"},
    {"name": "Unix Domain Socket to Squid", "category": "Proxy bypass", "description": "Connect to Squid via Unix socket", "result": "failure", "date": "2026-01-19", "details": "No Unix sockets found"},
    {"name": "Port 8080 HTTP Bypass", "category": "Protocol-level bypass", "description": "Connect to example.com:8080 (non-standard port)", "result": "failure", "date": "2026-01-19", "details": "Connection timeout - not redirected but blocked by DROP rule"},
    {"name": "HTTP TRACE Method", "category": "Application-level bypass", "description": "TRACE method to examine request path", "result": "failure", "date": "2026-01-19", "details": "400 Bad Request"},
    {"name": "HTTP Trailer Headers", "category": "Application-level smuggling", "description": "Trailer header with chunked encoding", "result": "failure", "date": "2026-01-19", "details": "400 Bad Request"},
    {"name": "Content-Length/Transfer-Encoding Conflict", "category": "Application-level smuggling", "description": "CL.TE desync attempt", "result": "failure", "date": "2026-01-19", "details": "400 Bad Request - Squid validates correctly"},
    {"name": "IPv4 Source Routing", "category": "Protocol-level bypass", "description": "Raw socket with IP_OPTIONS for source routing", "result": "failure", "date": "2026-01-19", "details": "CAP_NET_RAW not available"},
    {"name": "/sys/class/net Manipulation", "category": "Network stack manipulation", "description": "Access network interface sysfs entries", "result": "failure", "date": "2026-01-19", "details": "Readable but no escape path"},
    {"name": "Seccomp Profile Analysis", "category": "Container escape", "description": "Check seccomp filtering status", "result": "failure", "date": "2026-01-19", "details": "Seccomp mode 2 enabled with 1 filter"},
    {"name": "AppArmor Profile Discovery", "category": "Container escape", "description": "Check AppArmor confinement", "result": "failure", "date": "2026-01-19", "details": "docker-default profile enforced"},
    {"name": "DNS CAA Record Query", "category": "DNS-based attack", "description": "Query CAA record for example.com", "result": "failure", "date": "2026-01-19", "details": "DNS works but no HTTP path"},
    {"name": "DNS TLSA/DANE Record Query", "category": "DNS-based attack", "description": "Query TLSA record _443._tcp.example.com", "result": "failure", "date": "2026-01-19", "details": "DNS works but no HTTP path"},
    {"name": "Alternative Network Interfaces", "category": "Network stack manipulation", "description": "Search for additional network interfaces", "result": "failure", "date": "2026-01-19", "details": "ip command not available"},
    {"name": "Routing Table Analysis", "category": "Network stack manipulation", "description": "Examine /proc/net/route for escape paths", "result": "failure", "date": "2026-01-19", "details": "Standard routes, no bypass"},
    {"name": "iptables Rules Inspection", "category": "Network stack manipulation", "description": "Read iptables rules with iptables -L", "result": "failure", "date": "2026-01-19", "details": "Permission denied (must be root)"},
    {"name": "HTTP/1.0 Without Host Header", "category": "Application-level bypass", "description": "HTTP/1.0 GET / without Host header", "result": "failure", "date": "2026-01-19", "details": "400 Bad Request"},
    {"name": "Localhost HTTP Proxy (CONNECT)", "category": "Proxy bypass", "description": "Run local proxy on 127.0.0.1, tunnel to example.com", "result": "failure", "date": "2026-01-19", "details": "Connection succeeds but NAT still redirects to Squid"},
    {"name": "Localhost Proxy Data Transfer", "category": "Proxy bypass", "description": "Local proxy with TLS ClientHello relay", "result": "failure", "date": "2026-01-19", "details": "Connection succeeds but TLS handshake incomplete"},
    {"name": "Localhost Proxy HTTP GET", "category": "Proxy bypass", "description": "Local proxy forwarding HTTP GET to example.com", "result": "failure", "date": "2026-01-19", "details": "NAT redirects to Squid, 400 Bad Request"}
  ]
}
